seos/__init__.py
seos/seos.py
seos-0.3.5.dist-info/entry_points.txt
seos-0.3.5.dist-info/LICENSE
seos-0.3.5.dist-info/WHEEL
seos-0.3.5.dist-info/METADATA
seos-0.3.5.dist-info/RECORD
