Metadata-Version: 2.1
Name: seos
Version: 0.3.5
Summary: Simple Extractor on Sheets or SEOS wraps extraction on Google Sheets
Home-page: https://github.com/mamerisawesome/seos
License: BSD-3-Clause
Keywords: gsheets,google-sheets,sheets-scraping,python-scraping,data
Author: Almer Mendoza
Author-email: atmalmer23@gmail.com
Maintainer: Don Dilidili, Kiana Villaera
Requires-Python: >=3.6,<4.0
Classifier: License :: OSI Approved :: BSD License
Classifier: Programming Language :: Python :: 3
Classifier: Programming Language :: Python :: 3.6
Classifier: Programming Language :: Python :: 3.7
Classifier: Programming Language :: Python :: 3.8
Requires-Dist: google-api-python-client (>=1.7,<2.0)
Requires-Dist: google_auth_oauthlib (>=0.4.1,<0.5.0)
Requires-Dist: oauth2client (>=3,<4)
Requires-Dist: rainbow-bridge-logger (>=0.6.0,<0.7.0)
Project-URL: Repository, https://github.com/mamerisawesome/seos
